Metadata-Version: 2.1
Name: django-useraudit-4x
Version: 1.7.2
Summary: Django user audit utilities like logging user log in, disabling access when password expires or user is inactive
Home-page: https://github.com/codesjedi/django-useraudit
Author: Enrique Gimenez
Author-email: me@enrique.digital
License: UNKNOWN
Download-URL: https://github.com/codesjedi/django-useraudit/releases
Platform: UNKNOWN
Classifier: Framework :: Django
Classifier: Intended Audience :: Developers
Classifier: Intended Audience :: System Administrators
Classifier: License :: OSI Approved :: MIT License
Classifier: Operating System :: OS Independent
Classifier: Topic :: Software Development
License-File: LICENSE
